envrender
