Metadata-Version: 1.1
Name: env-render
Version: 0.1.2
Summary: Generates files by parsing the environment with jinja2
Home-page: https://github.com/virtru/env-render
Author: Reuven V. Gonzales
Author-email: reuven@virtru.com
License: MIT
Platform: *nix
Classifier: License :: OSI Approved :: MIT License
Classifier: Intended Audience :: Developers
Classifier: Programming Language :: Python
Classifier: Operating System :: POSIX
Classifier: Topic :: Software Development :: Build Tools
